[
  {
    "title": "测试数据0",
    "start_time": "2018-05-31",
    "end_time": "2018-06-01",
    "create_time": "2018-05-31"
  },
  {
    "title": "测试数据1",
    "start_time": "2018-05-24",
    "end_time": "2018-06-01",
    "create_time": "2018-05-31"
  },
  {
    "title": "测试数据2",
    "start_time": "2018-05-29",
    "end_time": "2018-06-03",
    "create_time": "2018-05-31"
  },
  {
    "title": "测试数据3",
    "start_time": "2018-05-28",
    "end_time": "2018-06-04",
    "create_time": "2018-05-28"
  },
  {
    "title": "测试数据4",
    "start_time": "2018-06-11",
    "end_time": "2018-07-15",
    "create_time": "2018-06-09"
  },
  {
    "title": "测试数据5",
    "start_time": "2018-05-25",
    "end_time": "2018-06-2",
    "create_time": "2018-06-2"
  },
  {
    "title": "测试数据6",
    "start_time": "2018-05-31",
    "end_time": "2018-06-01",
    "create_time": "2018-05-31"
  }
]